<?xml version="1.0"?>
<courseleaf>

<title>Neurology (NEU)</title>


<text>
<![CDATA[  
<div class="sc_sccoursedescs">
<div class="courseblock"><h3 class="cols noindent"><span class="text courseblockdetail detail-code margin--span text--semibold text--big"><b>NEU 103</b></span> <span class="text courseblockdetail detail-title margin--span text--semibold text--big"><b>— Human Clinical Neuroanatomy</b></span> <span class="text courseblockdetail detail-hours_html margin--span text--semibold text--big"><b>(4 units)</b></span> </h3><div class="noindent"></div><div class="noindent"><p class="courseblockextra noindent"><em>Course Description:</em> Clinically relevant anatomy of the normal human nervous system, including external and internal anatomy of the brain, spinal cord, and cranial nerves. Blood supply to the brain and spinal cord. Functional neuroanatomy of motor, sensory, and cognitive systems. Application of neuroanatomical principles relevant to clinical problem solving for students entering health care professions.</p></div><div class="noindent"><p class="text courseblockdetail detail-prerequisite"><i>Prerequisite(s): </i><span class="code_bubble" data-code-bubble="CHA 101">CHA 101</span>; or consent of instructor.</p></div><div class="noindent notinpdf"><div class="courseblockextra noindent"><h4 class="toggle bubble-hide"></h4>
<ul>
<li><span class="label"><em>Learning Activities:</em></span> Lecture 3 hour(s), Laboratory 3 hour(s).</li>
<li><span class="label"><em>Enrollment Restriction(s):</em></span> Open to upper division students.</li>
<li><span class="label"><em>Cross Listing:</em></span> <span class="code_bubble" data-code-bubble="CHA 103">CHA 103</span>.</li>
<li><span class="label"><em>Grade Mode:</em></span> Letter.</li>
<li><span class="label"><em>General Education:</em></span> Science &amp; Engineering (SE).</li></ul>
</div></div><div hidden="true" class="noindent"><div class="courseblockextra noindent"><div>
<em>Learning Activities: </em>Lecture 3 hour(s), Laboratory 3 hour(s).<br/><em>Enrollment Restriction(s): </em>Open to upper division students.<br/><em>Cross Listing: </em><span class="code_bubble" data-code-bubble="CHA 103">CHA 103</span>.<br/><em>Grade Mode: </em>Letter.<br/><em>General Education: </em>Science &amp; Engineering (SE).</div>
</div></div></div><div class="courseblock"><h3 class="cols noindent"><span class="text courseblockdetail detail-code margin--span text--semibold text--big"><b>NEU 199</b></span> <span class="text courseblockdetail detail-title margin--span text--semibold text--big"><b>— Individual Special Study &amp; Research</b></span> <span class="text courseblockdetail detail-hours_html margin--span text--semibold text--big"><b>(1-4 units)</b></span> </h3><div class="noindent"></div><div class="noindent"><p class="courseblockextra noindent"><em>Course Description:</em> Individual special study in neurophysiology and biomedical engineering is offered to qualified students. Studies on psychophysics, single-unit electrophysiology and instrumentation are offered in Davis.</p></div><div class="noindent"><p class="text courseblockdetail detail-prerequisite"><i>Prerequisite(s): </i>Consent of instructor.</p></div><div class="noindent notinpdf"><div class="courseblockextra noindent"><h4 class="toggle bubble-hide"></h4>
<ul>
<li><span class="label"><em>Learning Activities:</em></span> Variable.</li>
<li><span class="label"><em>Grade Mode:</em></span> Pass/No Pass only.</li></ul>
</div></div><div hidden="true" class="noindent"><div class="courseblockextra noindent"><div>
<em>Learning Activities: </em>Variable.<br/><em>Grade Mode: </em>Pass/No Pass only.</div>
</div></div></div><div class="courseblock"><h3 class="cols noindent"><span class="text courseblockdetail detail-code margin--span text--semibold text--big"><b>NEU 440</b></span> <span class="text courseblockdetail detail-title margin--span text--semibold text--big"><b>— Where Drugs Come From: How They are Discovered, Developed, Regulated, &amp; Marketed</b></span> <span class="text courseblockdetail detail-hours_html margin--span text--semibold text--big"><b>(3-6 units)</b></span> </h3><div class="noindent"></div><div class="noindent"><p class="courseblockextra noindent"><em>Course Description:</em> Includes the following topics: Overview of the Drug Discovery Process; Drug Regulation in the United States; Patents and Other Forms of Exclusivity; Drug Targets and Pharmacology; Identification of Lead Candidates; Preclinical Assessment; ADME Including Basic Pharmacokinetic Principles; Principles of Drug Toxicity; Principles of Drug Safety; Clinical Trials; Generic Drugs; Pharmaceutical Industry; Drug Distribution and Marketing; Dietary Supplements; Controlled Substances.</p></div><div class="noindent"></div><div class="noindent notinpdf"><div class="courseblockextra noindent"><h4 class="toggle bubble-hide"></h4>
<ul>
<li><span class="label"><em>Learning Activities:</em></span> Lecture.</li>
<li><span class="label"><em>Grade Mode:</em></span> Honors/Pass/Fail.</li></ul>
</div></div><div hidden="true" class="noindent"><div class="courseblockextra noindent"><div>
<em>Learning Activities: </em>Lecture.<br/><em>Grade Mode: </em>Honors/Pass/Fail.</div>
</div></div></div><div class="courseblock"><h3 class="cols noindent"><span class="text courseblockdetail detail-code margin--span text--semibold text--big"><b>NEU 450</b></span> <span class="text courseblockdetail detail-title margin--span text--semibold text--big"><b>— Clinical Neurology Clerkship</b></span> <span class="text courseblockdetail detail-hours_html margin--span text--semibold text--big"><b>(3-6 units)</b></span> </h3><div class="noindent"></div><div class="noindent"><p class="courseblockextra noindent"><em>Course Description:</em> Critical elements of neurological clinical skills (history &amp; exam) and basic and clinical neurological concepts expected for general residency preparation. Active, didactic, experiential and independent learning to encourage maturation of general professional competencies.</p></div><div class="noindent"><p class="text courseblockdetail detail-prerequisite"><i>Prerequisite(s): </i>Open to all fourth-year medical students; third-year medical students with consent of instructor.</p></div><div class="noindent notinpdf"><div class="courseblockextra noindent"><h4 class="toggle bubble-hide"></h4>
<ul>
<li><span class="label"><em>Learning Activities:</em></span> Clinical Activity 24 hour(s), Conference 12 hour(s), Seminar 4 hour(s), Independent Study 10 hour(s).</li>
<li><span class="label"><em>Enrollment Restriction(s):</em></span> Restricted to six students per rotation.</li>
<li><span class="label"><em>Repeat Credit:</em></span> May be repeated.</li>
<li><span class="label"><em>Grade Mode:</em></span> Honors/Pass/Fail.</li></ul>
</div></div><div hidden="true" class="noindent"><div class="courseblockextra noindent"><div>
<em>Learning Activities: </em>Clinical Activity 24 hour(s), Conference 12 hour(s), Seminar 4 hour(s), Independent Study 10 hour(s).<br/><em>Enrollment Restriction(s): </em>Restricted to six students per rotation.<br/><em>Repeat Credit: </em>May be repeated.<br/><em>Grade Mode: </em>Honors/Pass/Fail.</div>
</div></div></div><div class="courseblock"><h3 class="cols noindent"><span class="text courseblockdetail detail-code margin--span text--semibold text--big"><b>NEU 452</b></span> <span class="text courseblockdetail detail-title margin--span text--semibold text--big"><b>— Advanced Clinical Neurology</b></span> <span class="text courseblockdetail detail-hours_html margin--span text--semibold text--big"><b>(6 units)</b></span> </h3><div class="noindent"></div><div class="noindent"><p class="courseblockextra noindent"><em>Course Description:</em> Teaches the principles and skills necessary to recognize and manage the neurologic diseases a general medical practitioner is most likely to encounter in practice. Gain clinical experience in both inpatient and outpatient settings, and learn how to interview patients and their caregivers to obtain a complete and reliable neurologic history and perform a reliable neurologic examination.</p></div><div class="noindent"><p class="text courseblockdetail detail-prerequisite"><i>Prerequisite(s): </i>Consent of instructor; completion of four-week Neurology selective.</p></div><div class="noindent notinpdf"><div class="courseblockextra noindent"><h4 class="toggle bubble-hide"></h4>
<ul>
<li><span class="label"><em>Learning Activities:</em></span> Clinical Activity.</li>
<li><span class="label"><em>Grade Mode:</em></span> Honors/Pass/Fail.</li></ul>
</div></div><div hidden="true" class="noindent"><div class="courseblockextra noindent"><div>
<em>Learning Activities: </em>Clinical Activity.<br/><em>Grade Mode: </em>Honors/Pass/Fail.</div>
</div></div></div><div class="courseblock"><h3 class="cols noindent"><span class="text courseblockdetail detail-code margin--span text--semibold text--big"><b>NEU 455</b></span> <span class="text courseblockdetail detail-title margin--span text--semibold text--big"><b>— Child Neurology</b></span> <span class="text courseblockdetail detail-hours_html margin--span text--semibold text--big"><b>(1-12 units)</b></span> </h3><div class="noindent"></div><div class="noindent"><p class="courseblockextra noindent"><em>Course Description:</em> Exposure to children with disorders of the nervous system, both in outpatient and inpatient services. Cases presented to a member of full-time faculty who will discuss clinical findings, differential diagnosis, management and therapy. Satisfies fourth-year neuroscience requirement.</p></div><div class="noindent"><p class="text courseblockdetail detail-prerequisite"><i>Prerequisite(s): </i><span class="code_bubble" data-code-bubble="IMD 430">IMD 430</span>; <span class="code_bubble" data-code-bubble="OBG 430">OBG 430</span>; <span class="code_bubble" data-code-bubble="PED 430">PED 430</span>; consent of instructor.</p></div><div class="noindent notinpdf"><div class="courseblockextra noindent"><h4 class="toggle bubble-hide"></h4>
<ul>
<li><span class="label"><em>Learning Activities:</em></span> Clinical Activity.</li>
<li><span class="label"><em>Grade Mode:</em></span> Honors/Pass/Fail.</li></ul>
</div></div><div hidden="true" class="noindent"><div class="courseblockextra noindent"><div>
<em>Learning Activities: </em>Clinical Activity.<br/><em>Grade Mode: </em>Honors/Pass/Fail.</div>
</div></div></div><div class="courseblock"><h3 class="cols noindent"><span class="text courseblockdetail detail-code margin--span text--semibold text--big"><b>NEU 460</b></span> <span class="text courseblockdetail detail-title margin--span text--semibold text--big"><b>— Externship in Neurology</b></span> <span class="text courseblockdetail detail-hours_html margin--span text--semibold text--big"><b>(3-6 units)</b></span> </h3><div class="noindent"></div><div class="noindent"><p class="courseblockextra noindent"><em>Course Description:</em> Externship course for Neurology rotations not meeting the qualifications to be an Acting Internship.</p></div><div class="noindent"><p class="text courseblockdetail detail-prerequisite"><i>Prerequisite(s): </i>Consent of instructor.</p></div><div class="noindent notinpdf"><div class="courseblockextra noindent"><h4 class="toggle bubble-hide"></h4>
<ul>
<li><span class="label"><em>Learning Activities:</em></span> Clinical Activity.</li>
<li><span class="label"><em>Repeat Credit:</em></span> May be repeated.</li>
<li><span class="label"><em>Grade Mode:</em></span> Honors/Pass/Fail.</li></ul>
</div></div><div hidden="true" class="noindent"><div class="courseblockextra noindent"><div>
<em>Learning Activities: </em>Clinical Activity.<br/><em>Repeat Credit: </em>May be repeated.<br/><em>Grade Mode: </em>Honors/Pass/Fail.</div>
</div></div></div><div class="courseblock"><h3 class="cols noindent"><span class="text courseblockdetail detail-code margin--span text--semibold text--big"><b>NEU 462</b></span> <span class="text courseblockdetail detail-title margin--span text--semibold text--big"><b>— Externship in Advanced Neurology</b></span> <span class="text courseblockdetail detail-hours_html margin--span text--semibold text--big"><b>(3-6 units)</b></span> </h3><div class="noindent"></div><div class="noindent"><p class="courseblockextra noindent"><em>Course Description:</em> Away rotation in Neurology where coursework meets the standards to be counted as an Acting Internship.</p></div><div class="noindent"><p class="text courseblockdetail detail-prerequisite"><i>Prerequisite(s): </i>Consent of instructor.</p></div><div class="noindent notinpdf"><div class="courseblockextra noindent"><h4 class="toggle bubble-hide"></h4>
<ul>
<li><span class="label"><em>Learning Activities:</em></span> Clinical Activity.</li>
<li><span class="label"><em>Grade Mode:</em></span> Honors/Pass/Fail.</li></ul>
</div></div><div hidden="true" class="noindent"><div class="courseblockextra noindent"><div>
<em>Learning Activities: </em>Clinical Activity.<br/><em>Grade Mode: </em>Honors/Pass/Fail.</div>
</div></div></div><div class="courseblock"><h3 class="cols noindent"><span class="text courseblockdetail detail-code margin--span text--semibold text--big"><b>NEU 499</b></span> <span class="text courseblockdetail detail-title margin--span text--semibold text--big"><b>— Research </b></span> <span class="text courseblockdetail detail-hours_html margin--span text--semibold text--big"><b>(1-12 units)</b></span> </h3><div class="noindent"></div><div class="noindent"><p class="courseblockextra noindent"><em>Course Description:</em> Approved for graduate degree credit. Laboratory investigation on selected topics.</p></div><div class="noindent"><p class="text courseblockdetail detail-prerequisite"><i>Prerequisite(s): </i>Consent of instructor.</p></div><div class="noindent notinpdf"><div class="courseblockextra noindent"><h4 class="toggle bubble-hide"></h4>
<ul>
<li><span class="label"><em>Learning Activities:</em></span> Laboratory 2-24 hour(s).</li>
<li><span class="label"><em>Repeat Credit:</em></span> May be repeated.</li>
<li><span class="label"><em>Grade Mode:</em></span> Honors/Pass/Fail.</li></ul>
</div></div><div hidden="true" class="noindent"><div class="courseblockextra noindent"><div>
<em>Learning Activities: </em>Laboratory 2-24 hour(s).<br/><em>Repeat Credit: </em>May be repeated.<br/><em>Grade Mode: </em>Honors/Pass/Fail.</div>
</div></div></div></div>
  
]]>
</text>
<faculty>
<![CDATA[
]]>
</faculty>
</courseleaf>

