<?xml version="1.0"?>
<courseleaf>

<title>Construction Engineering &amp; Management, Minor</title>


<text>
<![CDATA[  

  
]]>
</text>
<informationtext name="Information">
<![CDATA[
<p>California's construction industry continues to experience high growth as it continues to accommodate an increasing population and as it faces renewal of much of the infrastructure built by previous generations. At the same time, the construction industry faces challenges of scarce materials, a need for decreased environmental impact in terms of the construction process itself and operation of the completed project, and a more complex operational, regulatory and social context in which it must do its work.</p>
<p>The purpose of this minor is to better prepare professional civil and environmental engineers to thrive in this challenging industry and to improve the efficiency of delivery and sustainability of the civil infrastructure in the state through their future efforts.</p>
<p>It is expected that engineering students will enroll in this minor program, including Civil, Mechanical, Chemical, and Materials Science majors. Students from other colleges can also complete this minor, but it is recommended that they review the requirements with one of the advisors before enrolling. Students who are interested in the construction of infrastructure in their discipline can make use of the skills that will be learned through the completion of this minor.</p>
<p>All courses must be taken for a letter grade. A grade of C- or better is required for all courses used to satisfy minor requirements, with an overall GPA of 2.000 or better. All prerequisites for courses must have been taken for a letter grade; no grade lower than a C- will be accepted in any prerequisite course. </p>
<p>The online Minor Declaration form is available via the <a href="https://students.ucdavis.edu/">Online Advising Student Information System (OASIS)</a>. For more information, contact the <a href="mailto:civiladvising@ucdavis.edu">undergraduate advisors</a> in the Department of Civil &amp; Environmental Engineering.</p>
<p>Transcript notation must be requested no later than the quarter preceding graduation, and will appear as a minor in Construction Engineering &amp; Management.</p>
<h2>Course Overlap</h2>
<p>Please refer to your college’s policies regarding overlap rules.</p>
<h2>Minor Advisors</h2>
<p>C. Bronner, S. Miller, J. Bolander, S. Nassiri</p>
]]>
</informationtext>
<requirementstext name="Requirements">
<![CDATA[
<table class="sc_courselist">
<caption class="hidden noscript">Course List</caption>
<colgroup>
<col class="codecol"/>
<col class="titlecol"/>
<col align="char" char="." class="hourscol"/>
</colgroup>
<thead>
<tr class="hidden noscript">
<th scope="col">Code</th>
<th scope="col">Title</th>
<th scope="col" class="hourscol">Units</th>
</tr>
</thead>
<tbody>
<tr class="even areasubheader undefined firstrow"><td colspan="2"><span class="courselistcomment areasubheader undefined">Civil &amp; Environmental Engineering</span></td><td class="hourscol">8</td></tr>
<tr class="odd"><td class="codecol"><div style="margin-left:20px;" class="blockindent"><span class="code_bubble" data-code-bubble="ECI 137">ECI 137</span></div></td><td>Construction Principles &amp; Project Management</td><td class="hourscol"></td></tr>
<tr class="even"><td class="codecol"><div style="margin-left:20px;" class="blockindent"><span class="code_bubble" data-code-bubble="ECI 153">ECI 153</span></div></td><td>Deterministic Optimization &amp; Design</td><td class="hourscol"></td></tr>
<tr class="odd areasubheader undefined"><td colspan="2"><span class="courselistcomment areasubheader undefined">Sustainability Requirement; choose one:</span></td><td class="hourscol">4</td></tr>
<tr class="even"><td class="codecol"><div style="margin-left:20px;" class="blockindent"><span class="code_bubble" data-code-bubble="ECI 123">ECI 123</span></div></td><td>Urban Systems &amp; Sustainability</td><td class="hourscol"></td></tr>
<tr class="odd"><td class="codecol"><div style="margin-left:20px;" class="blockindent"><span class="code_bubble" data-code-bubble="ECI 133">ECI 133</span></div></td><td>Structure &amp; Properties of Civil Engineering Materials <sup>1</sup></td><td class="hourscol"></td></tr>
<tr class="even areasubheader undefined"><td colspan="2"><span class="courselistcomment areasubheader undefined">Engineering Requirement; choose two:</span></td><td class="hourscol">8</td></tr>
<tr class="odd"><td class="codecol"><div style="margin-left:20px;" class="blockindent"><span class="code_bubble" data-code-bubble="ECI 133">ECI 133</span></div></td><td>Structure &amp; Properties of Civil Engineering Materials <sup>1</sup></td><td class="hourscol"></td></tr>
<tr class="even"><td class="codecol"><div style="margin-left:20px;" class="blockindent"><span class="code_bubble" data-code-bubble="ECI 178">ECI 178</span></div></td><td>Pavement Engineering &amp; Design</td><td class="hourscol"></td></tr>
<tr class="odd"><td class="codecol"><div style="margin-left:20px;" class="blockindent"><span class="code_bubble" data-code-bubble="ECI 179">ECI 179</span></div></td><td>Pavement Management, Evaluation, &amp; Rehabilitation</td><td class="hourscol"></td></tr>
<tr class="even"><td class="codecol"><div style="margin-left:20px;" class="blockindent"><span class="code_bubble" data-code-bubble="ECI 181">ECI 181</span></div></td><td>Construction Cost Estimation &amp; Analysis</td><td class="hourscol"></td></tr>
<tr class="odd"><td class="codecol"><div style="margin-left:20px;" class="blockindent"><span class="code_bubble" data-code-bubble="ECI 182">ECI 182</span></div></td><td>Buildings: Assemblage &amp; Construction Quality Management</td><td class="hourscol"></td></tr>
<tr class="even"><td class="codecol"><div style="margin-left:20px;" class="blockindent"><span class="code_bubble" data-code-bubble="ECI 183">ECI 183</span></div></td><td>Heavy Civil Construction</td><td class="hourscol"></td></tr>
<tr class="odd areasubheader undefined"><td colspan="2"><span class="courselistcomment areasubheader undefined">Economics &amp; Law Requirement; choose two:</span></td><td class="hourscol">8</td></tr>
<tr class="even"><td class="codecol"><div style="margin-left:20px;" class="blockindent"><span class="code_bubble" data-code-bubble="ARE 018">ARE 018</span></div></td><td>Business Law <sup>2</sup></td><td class="hourscol"></td></tr>
<tr class="odd"><td class="codecol"><div style="margin-left:20px;" class="blockindent"><span class="code_bubble" data-code-bubble="ARE 112">ARE 112</span></div></td><td>Fundamentals of Organization Management</td><td class="hourscol"></td></tr>
<tr class="even"><td class="codecol"><div style="margin-left:20px;" class="blockindent"><span class="code_bubble" data-code-bubble="ARE 118">ARE 118</span></div></td><td>Tax Accounting</td><td class="hourscol"></td></tr>
<tr class="odd"><td class="codecol"><div style="margin-left:20px;" class="blockindent"><span class="code_bubble" data-code-bubble="ARE 155">ARE 155</span></div></td><td>Operations Research &amp; Management Science</td><td class="hourscol"></td></tr>
<tr class="even"><td class="codecol"><div style="margin-left:20px;" class="blockindent"><span class="code_bubble" data-code-bubble="ARE 157">ARE 157</span></div></td><td>Analysis for Operations &amp; Production Management</td><td class="hourscol"></td></tr>
<tr class="odd"><td class="codecol"><div style="margin-left:20px;" class="blockindent"><span class="code_bubble" data-code-bubble="ECN 134">ECN 134</span></div></td><td>Financial Economics</td><td class="hourscol"></td></tr>
<tr class="orclass odd"><td class="codecol orclass"><div style="margin-left:20px;" class="blockindent">or <span class="code_bubble" data-code-bubble="ECN 134Y">ECN 134Y</span></div></td><td colspan="2"> Financial Economics</td></tr>
<tr class="even"><td class="codecol"><div style="margin-left:20px;" class="blockindent"><span class="code_bubble" data-code-bubble="ECN 162">ECN 162</span></div></td><td>International Economic Relations</td><td class="hourscol"></td></tr>
<tr class="orclass even"><td class="codecol orclass"><div style="margin-left:20px;" class="blockindent">or <span class="code_bubble" data-code-bubble="ECN 162Y">ECN 162Y</span></div></td><td colspan="2"> International Economic Relations</td></tr>
<tr class="odd"><td class="codecol"><div style="margin-left:20px;" class="blockindent"><span class="code_bubble" data-code-bubble="ESP 161">ESP 161</span></div></td><td>Environmental Law</td><td class="hourscol"></td></tr>
<tr class="even lastrow"><td class="codecol"><div style="margin-left:20px;" class="blockindent"><span class="code_bubble" data-code-bubble="MGT 011A">MGT 011A</span></div></td><td>Elementary Financial Accounting <sup>2</sup></td><td class="hourscol"></td></tr>
<tr class="listsum"><td colspan="2">Total Units</td><td class="hourscol">28</td></tr></tbody>
</table>

<dl class="sc_footnotes" aria-label="Footnotes"><dt> <sup> 1 </sup> </dt><dd><p class="noindent"><span class="sc_courseinline"><span class="code_bubble" data-code-bubble="ECI 133">ECI 133</span></span>​ may be used <span style="font-family:proxima-nova,system-ui,-apple-system,blinkmacsystemfont,segoe ui,roboto,ubuntu,helvetica neue,arial,sans-serif,apple color emoji,segoe ui emoji,segoe ui symbol; font-size:16px; font-style:normal; font-variant-caps:normal; font-variant-ligatures:normal; font-weight:400">only </span>once; may be used for the <em>Sustainability Requirement</em> or the <em>Engineering Requirement</em>.</p></dd><dt> <sup> 2 </sup> </dt><dd><p class="noindent">Students may take <span style="font-family:proxima-nova,system-ui,-apple-system,blinkmacsystemfont,segoe ui,roboto,ubuntu,helvetica neue,arial,sans-serif,apple color emoji,segoe ui emoji,segoe ui symbol; font-size:16px; font-style:normal; font-variant-caps:normal; font-variant-ligatures:normal; font-weight:400">only </span>one lower-division course for the minor.</p></dd></dl>
]]>
</requirementstext>
<quickviewtext name="Quick View">
<![CDATA[
<p>The <span class="title-main">Construction Engineering &amp; Management </span>minor prepares professional civil &amp; environmental engineers to thrive in the challenging construction industry and to improve the efficiency of delivery &amp; sustainability of the civil infrastructure through their future efforts.</p>
]]>
</quickviewtext>
<faculty>
<![CDATA[
]]>
</faculty>
</courseleaf>

