<?xml version="1.0"?>
<courseleaf>

<title>Music, Doctor of Philosophy</title>


<text>
<![CDATA[  

  
]]>
</text>
<informationtext name="Information">
<![CDATA[
<h2>Graduate Study</h2>
<p>The Department of Music offers programs of study and research leading to the M.A. degree in composition/theory, musicology, ethnomusicology, and conducting, and the Ph.D. degree in composition/theory, musicology, and ethnomusicology. Detailed information regarding graduate study may be obtained from the Graduate Advisor.</p>
<h3>Degree Requirements &amp; Program Coordinator</h3>
<p>See <a href="https://grad.ucdavis.edu/programs/gmus">Music</a>.</p>
]]>
</informationtext>
<quickviewtext name="Quick View">
<![CDATA[
<p>The program of study provides a common core of training and specializations in composition/theory, musicology, or ethnomusicology. </p>
]]>
</quickviewtext>
<faculty>
<![CDATA[
]]>
</faculty>
</courseleaf>

